{
    "os": "Linux-5.4.0-80-generic-x86_64-with-glibc2.31",
    "python": "3.10.14",
    "heartbeatAt": "2024-05-19T14:47:42.490892",
    "startedAt": "2024-05-19T14:47:41.644942",
    "docker": null,
    "cuda": null,
    "args": [
        "--activation=ReLU",
        "--alpha=0.0001",
        "--batch_size=64",
        "--beta1=0.9",
        "--epochs=10",
        "--hidden_sizes=64",
        "--learning_rate=0.01",
        "--loss=cross_entropy",
        "--num_layers=5",
        "--optimizer=sgd",
        "--weight_init=he"
    ],
    "state": "running",
    "program": "/nlsasfs/home/ai4bharat/praveens/srija/assignment_1/train.py",
    "codePathLocal": "train.py",
    "codePath": "train.py",
    "host": "scn28-mn",
    "username": "praveens",
    "executable": "/nlsasfs/home/ai4bharat/praveens/miniconda3/envs/dl_as/bin/python",
    "cpu_count": 128,
    "cpu_count_logical": 256,
    "cpu_freq": {
        "current": 2979.510433593749,
        "min": 1500.0,
        "max": 2250.0
    },
    "cpu_freq_per_core": [
        {
            "current": 3348.145,
            "min": 1500.0,
            "max": 2250.0
        },
        {
            "current": 3347.807,
            "min": 1500.0,
            "max": 2250.0
        },
        {
            "current": 3347.997,
            "min": 1500.0,
            "max": 2250.0
        },
        {
            "current": 3348.219,
            "min": 1500.0,
            "max": 2250.0
        },
        {
            "current": 3339.568,
            "min": 1500.0,
            "max": 2250.0
        },
        {
            "current": 3339.718,
            "min": 1500.0,
            "max": 2250.0
        },
        {
            "current": 3339.659,
            "min": 1500.0,
            "max": 2250.0
        },
        {
            "current": 3339.471,
            "min": 1500.0,
            "max": 2250.0
        },
        {
            "current": 3368.497,
            "min": 1500.0,
            "max": 2250.0
        },
        {
            "current": 3365.516,
            "min": 1500.0,
            "max": 2250.0
        },
        {
            "current": 3361.819,
            "min": 1500.0,
            "max": 2250.0
        },
        {
            "current": 3358.875,
            "min": 1500.0,
            "max": 2250.0
        },
        {
            "current": 3371.23,
            "min": 1500.0,
            "max": 2250.0
        },
        {
            "current": 3377.324,
            "min": 1500.0,
            "max": 2250.0
        },
        {
            "current": 3365.454,
            "min": 1500.0,
            "max": 2250.0
        },
        {
            "current": 3366.892,
            "min": 1500.0,
            "max": 2250.0
        },
        {
            "current": 3344.85,
            "min": 1500.0,
            "max": 2250.0
        },
        {
            "current": 3345.046,
            "min": 1500.0,
            "max": 2250.0
        },
        {
            "current": 3344.811,
            "min": 1500.0,
            "max": 2250.0
        },
        {
            "current": 3344.869,
            "min": 1500.0,
            "max": 2250.0
        },
        {
            "current": 3326.073,
            "min": 1500.0,
            "max": 2250.0
        },
        {
            "current": 3326.7,
            "min": 1500.0,
            "max": 2250.0
        },
        {
            "current": 3326.586,
            "min": 1500.0,
            "max": 2250.0
        },
        {
            "current": 3326.77,
            "min": 1500.0,
            "max": 2250.0
        },
        {
            "current": 3377.921,
            "min": 1500.0,
            "max": 2250.0
        },
        {
            "current": 2548.597,
            "min": 1500.0,
            "max": 2250.0
        },
        {
            "current": 3374.542,
            "min": 1500.0,
            "max": 2250.0
        },
        {
            "current": 3375.468,
            "min": 1500.0,
            "max": 2250.0
        },
        {
            "current": 2540.807,
            "min": 1500.0,
            "max": 2250.0
        },
        {
            "current": 3258.492,
            "min": 1500.0,
            "max": 2250.0
        },
        {
            "current": 3355.26,
            "min": 1500.0,
            "max": 2250.0
        },
        {
            "current": 3373.062,
            "min": 1500.0,
            "max": 2250.0
        },
        {
            "current": 3369.031,
            "min": 1500.0,
            "max": 2250.0
        },
        {
            "current": 3368.05,
            "min": 1500.0,
            "max": 2250.0
        },
        {
            "current": 3367.66,
            "min": 1500.0,
            "max": 2250.0
        },
        {
            "current": 3365.579,
            "min": 1500.0,
            "max": 2250.0
        },
        {
            "current": 3362.66,
            "min": 1500.0,
            "max": 2250.0
        },
        {
            "current": 3376.823,
            "min": 1500.0,
            "max": 2250.0
        },
        {
            "current": 3367.099,
            "min": 1500.0,
            "max": 2250.0
        },
        {
            "current": 3375.626,
            "min": 1500.0,
            "max": 2250.0
        },
        {
            "current": 3382.159,
            "min": 1500.0,
            "max": 2250.0
        },
        {
            "current": 3349.057,
            "min": 1500.0,
            "max": 2250.0
        },
        {
            "current": 3369.02,
            "min": 1500.0,
            "max": 2250.0
        },
        {
            "current": 3356.449,
            "min": 1500.0,
            "max": 2250.0
        },
        {
            "current": 3362.304,
            "min": 1500.0,
            "max": 2250.0
        },
        {
            "current": 3370.182,
            "min": 1500.0,
            "max": 2250.0
        },
        {
            "current": 3363.799,
            "min": 1500.0,
            "max": 2250.0
        },
        {
            "current": 3379.122,
            "min": 1500.0,
            "max": 2250.0
        },
        {
            "current": 3366.307,
            "min": 1500.0,
            "max": 2250.0
        },
        {
            "current": 3367.128,
            "min": 1500.0,
            "max": 2250.0
        },
        {
            "current": 3364.62,
            "min": 1500.0,
            "max": 2250.0
        },
        {
            "current": 2590.388,
            "min": 1500.0,
            "max": 2250.0
        },
        {
            "current": 3369.188,
            "min": 1500.0,
            "max": 2250.0
        },
        {
            "current": 3368.445,
            "min": 1500.0,
            "max": 2250.0
        },
        {
            "current": 3366.141,
            "min": 1500.0,
            "max": 2250.0
        },
        {
            "current": 3369.919,
            "min": 1500.0,
            "max": 2250.0
        },
        {
            "current": 3367.331,
            "min": 1500.0,
            "max": 2250.0
        },
        {
            "current": 3369.602,
            "min": 1500.0,
            "max": 2250.0
        },
        {
            "current": 3379.26,
            "min": 1500.0,
            "max": 2250.0
        },
        {
            "current": 3377.742,
            "min": 1500.0,
            "max": 2250.0
        },
        {
            "current": 2914.72,
            "min": 1500.0,
            "max": 2250.0
        },
        {
            "current": 3366.866,
            "min": 1500.0,
            "max": 2250.0
        },
        {
            "current": 3361.296,
            "min": 1500.0,
            "max": 2250.0
        },
        {
            "current": 3354.959,
            "min": 1500.0,
            "max": 2250.0
        },
        {
            "current": 3382.682,
            "min": 1500.0,
            "max": 2250.0
        },
        {
            "current": 2323.388,
            "min": 1500.0,
            "max": 2250.0
        },
        {
            "current": 3388.129,
            "min": 1500.0,
            "max": 2250.0
        },
        {
            "current": 2282.941,
            "min": 1500.0,
            "max": 2250.0
        },
        {
            "current": 3382.961,
            "min": 1500.0,
            "max": 2250.0
        },
        {
            "current": 3383.1,
            "min": 1500.0,
            "max": 2250.0
        },
        {
            "current": 3392.118,
            "min": 1500.0,
            "max": 2250.0
        },
        {
            "current": 3384.157,
            "min": 1500.0,
            "max": 2250.0
        },
        {
            "current": 3388.845,
            "min": 1500.0,
            "max": 2250.0
        },
        {
            "current": 3387.446,
            "min": 1500.0,
            "max": 2250.0
        },
        {
            "current": 3376.208,
            "min": 1500.0,
            "max": 2250.0
        },
        {
            "current": 3381.013,
            "min": 1500.0,
            "max": 2250.0
        },
        {
            "current": 3387.12,
            "min": 1500.0,
            "max": 2250.0
        },
        {
            "current": 3383.336,
            "min": 1500.0,
            "max": 2250.0
        },
        {
            "current": 3382.319,
            "min": 1500.0,
            "max": 2250.0
        },
        {
            "current": 2267.167,
            "min": 1500.0,
            "max": 2250.0
        },
        {
            "current": 2341.282,
            "min": 1500.0,
            "max": 2250.0
        },
        {
            "current": 3380.257,
            "min": 1500.0,
            "max": 2250.0
        },
        {
            "current": 3392.028,
            "min": 1500.0,
            "max": 2250.0
        },
        {
            "current": 3380.676,
            "min": 1500.0,
            "max": 2250.0
        },
        {
            "current": 3383.537,
            "min": 1500.0,
            "max": 2250.0
        },
        {
            "current": 3394.675,
            "min": 1500.0,
            "max": 2250.0
        },
        {
            "current": 3389.719,
            "min": 1500.0,
            "max": 2250.0
        },
        {
            "current": 3385.336,
            "min": 1500.0,
            "max": 2250.0
        },
        {
            "current": 3393.862,
            "min": 1500.0,
            "max": 2250.0
        },
        {
            "current": 3394.965,
            "min": 1500.0,
            "max": 2250.0
        },
        {
            "current": 3389.242,
            "min": 1500.0,
            "max": 2250.0
        },
        {
            "current": 3401.574,
            "min": 1500.0,
            "max": 2250.0
        },
        {
            "current": 3399.781,
            "min": 1500.0,
            "max": 2250.0
        },
        {
            "current": 3379.288,
            "min": 1500.0,
            "max": 2250.0
        },
        {
            "current": 3391.502,
            "min": 1500.0,
            "max": 2250.0
        },
        {
            "current": 3380.103,
            "min": 1500.0,
            "max": 2250.0
        },
        {
            "current": 3394.322,
            "min": 1500.0,
            "max": 2250.0
        },
        {
            "current": 3389.289,
            "min": 1500.0,
            "max": 2250.0
        },
        {
            "current": 2253.381,
            "min": 1500.0,
            "max": 2250.0
        },
        {
            "current": 3391.526,
            "min": 1500.0,
            "max": 2250.0
        },
        {
            "current": 3393.471,
            "min": 1500.0,
            "max": 2250.0
        },
        {
            "current": 3389.354,
            "min": 1500.0,
            "max": 2250.0
        },
        {
            "current": 3390.504,
            "min": 1500.0,
            "max": 2250.0
        },
        {
            "current": 3392.004,
            "min": 1500.0,
            "max": 2250.0
        },
        {
            "current": 3155.733,
            "min": 1500.0,
            "max": 2250.0
        },
        {
            "current": 3274.372,
            "min": 1500.0,
            "max": 2250.0
        },
        {
            "current": 3392.335,
            "min": 1500.0,
            "max": 2250.0
        },
        {
            "current": 1737.691,
            "min": 1500.0,
            "max": 2250.0
        },
        {
            "current": 2446.978,
            "min": 1500.0,
            "max": 2250.0
        },
        {
            "current": 2483.933,
            "min": 1500.0,
            "max": 2250.0
        },
        {
            "current": 3384.547,
            "min": 1500.0,
            "max": 2250.0
        },
        {
            "current": 3394.162,
            "min": 1500.0,
            "max": 2250.0
        },
        {
            "current": 1810.0,
            "min": 1500.0,
            "max": 2250.0
        },
        {
            "current": 3225.574,
            "min": 1500.0,
            "max": 2250.0
        },
        {
            "current": 2387.842,
            "min": 1500.0,
            "max": 2250.0
        },
        {
            "current": 2662.804,
            "min": 1500.0,
            "max": 2250.0
        },
        {
            "current": 3382.624,
            "min": 1500.0,
            "max": 2250.0
        },
        {
            "current": 2353.595,
            "min": 1500.0,
            "max": 2250.0
        },
        {
            "current": 2334.0,
            "min": 1500.0,
            "max": 2250.0
        },
        {
            "current": 2343.874,
            "min": 1500.0,
            "max": 2250.0
        },
        {
            "current": 3386.124,
            "min": 1500.0,
            "max": 2250.0
        },
        {
            "current": 2382.786,
            "min": 1500.0,
            "max": 2250.0
        },
        {
            "current": 3393.052,
            "min": 1500.0,
            "max": 2250.0
        },
        {
            "current": 3401.905,
            "min": 1500.0,
            "max": 2250.0
        },
        {
            "current": 2667.981,
            "min": 1500.0,
            "max": 2250.0
        },
        {
            "current": 3393.489,
            "min": 1500.0,
            "max": 2250.0
        },
        {
            "current": 3395.303,
            "min": 1500.0,
            "max": 2250.0
        },
        {
            "current": 3392.46,
            "min": 1500.0,
            "max": 2250.0
        },
        {
            "current": 3344.181,
            "min": 1500.0,
            "max": 2250.0
        },
        {
            "current": 3344.038,
            "min": 1500.0,
            "max": 2250.0
        },
        {
            "current": 3344.945,
            "min": 1500.0,
            "max": 2250.0
        },
        {
            "current": 3345.662,
            "min": 1500.0,
            "max": 2250.0
        },
        {
            "current": 3320.68,
            "min": 1500.0,
            "max": 2250.0
        },
        {
            "current": 3320.773,
            "min": 1500.0,
            "max": 2250.0
        },
        {
            "current": 3320.743,
            "min": 1500.0,
            "max": 2250.0
        },
        {
            "current": 3320.313,
            "min": 1500.0,
            "max": 2250.0
        },
        {
            "current": 3361.315,
            "min": 1500.0,
            "max": 2250.0
        },
        {
            "current": 3354.219,
            "min": 1500.0,
            "max": 2250.0
        },
        {
            "current": 3356.931,
            "min": 1500.0,
            "max": 2250.0
        },
        {
            "current": 3379.492,
            "min": 1500.0,
            "max": 2250.0
        },
        {
            "current": 3367.779,
            "min": 1500.0,
            "max": 2250.0
        },
        {
            "current": 3367.025,
            "min": 1500.0,
            "max": 2250.0
        },
        {
            "current": 2231.594,
            "min": 1500.0,
            "max": 2250.0
        },
        {
            "current": 3355.27,
            "min": 1500.0,
            "max": 2250.0
        },
        {
            "current": 3335.25,
            "min": 1500.0,
            "max": 2250.0
        },
        {
            "current": 3335.161,
            "min": 1500.0,
            "max": 2250.0
        },
        {
            "current": 3334.524,
            "min": 1500.0,
            "max": 2250.0
        },
        {
            "current": 3334.881,
            "min": 1500.0,
            "max": 2250.0
        },
        {
            "current": 3301.635,
            "min": 1500.0,
            "max": 2250.0
        },
        {
            "current": 3302.115,
            "min": 1500.0,
            "max": 2250.0
        },
        {
            "current": 3302.235,
            "min": 1500.0,
            "max": 2250.0
        },
        {
            "current": 3301.931,
            "min": 1500.0,
            "max": 2250.0
        },
        {
            "current": 3367.538,
            "min": 1500.0,
            "max": 2250.0
        },
        {
            "current": 3368.299,
            "min": 1500.0,
            "max": 2250.0
        },
        {
            "current": 3367.641,
            "min": 1500.0,
            "max": 2250.0
        },
        {
            "current": 3363.9,
            "min": 1500.0,
            "max": 2250.0
        },
        {
            "current": 3361.081,
            "min": 1500.0,
            "max": 2250.0
        },
        {
            "current": 3367.238,
            "min": 1500.0,
            "max": 2250.0
        },
        {
            "current": 3372.874,
            "min": 1500.0,
            "max": 2250.0
        },
        {
            "current": 3366.259,
            "min": 1500.0,
            "max": 2250.0
        },
        {
            "current": 3361.309,
            "min": 1500.0,
            "max": 2250.0
        },
        {
            "current": 3357.877,
            "min": 1500.0,
            "max": 2250.0
        },
        {
            "current": 2404.046,
            "min": 1500.0,
            "max": 2250.0
        },
        {
            "current": 3367.664,
            "min": 1500.0,
            "max": 2250.0
        },
        {
            "current": 3368.823,
            "min": 1500.0,
            "max": 2250.0
        },
        {
            "current": 3365.626,
            "min": 1500.0,
            "max": 2250.0
        },
        {
            "current": 3379.032,
            "min": 1500.0,
            "max": 2250.0
        },
        {
            "current": 3372.808,
            "min": 1500.0,
            "max": 2250.0
        },
        {
            "current": 3360.427,
            "min": 1500.0,
            "max": 2250.0
        },
        {
            "current": 3370.411,
            "min": 1500.0,
            "max": 2250.0
        },
        {
            "current": 3370.017,
            "min": 1500.0,
            "max": 2250.0
        },
        {
            "current": 3358.859,
            "min": 1500.0,
            "max": 2250.0
        },
        {
            "current": 2341.988,
            "min": 1500.0,
            "max": 2250.0
        },
        {
            "current": 3373.14,
            "min": 1500.0,
            "max": 2250.0
        },
        {
            "current": 3367.059,
            "min": 1500.0,
            "max": 2250.0
        },
        {
            "current": 3358.088,
            "min": 1500.0,
            "max": 2250.0
        },
        {
            "current": 3363.93,
            "min": 1500.0,
            "max": 2250.0
        },
        {
            "current": 3366.438,
            "min": 1500.0,
            "max": 2250.0
        },
        {
            "current": 3366.506,
            "min": 1500.0,
            "max": 2250.0
        },
        {
            "current": 3366.679,
            "min": 1500.0,
            "max": 2250.0
        },
        {
            "current": 3361.322,
            "min": 1500.0,
            "max": 2250.0
        },
        {
            "current": 3353.733,
            "min": 1500.0,
            "max": 2250.0
        },
        {
            "current": 3366.055,
            "min": 1500.0,
            "max": 2250.0
        },
        {
            "current": 3359.798,
            "min": 1500.0,
            "max": 2250.0
        },
        {
            "current": 3359.997,
            "min": 1500.0,
            "max": 2250.0
        },
        {
            "current": 3369.003,
            "min": 1500.0,
            "max": 2250.0
        },
        {
            "current": 3365.42,
            "min": 1500.0,
            "max": 2250.0
        },
        {
            "current": 3351.886,
            "min": 1500.0,
            "max": 2250.0
        },
        {
            "current": 3361.931,
            "min": 1500.0,
            "max": 2250.0
        },
        {
            "current": 3364.206,
            "min": 1500.0,
            "max": 2250.0
        },
        {
            "current": 3363.24,
            "min": 1500.0,
            "max": 2250.0
        },
        {
            "current": 3352.673,
            "min": 1500.0,
            "max": 2250.0
        },
        {
            "current": 3379.192,
            "min": 1500.0,
            "max": 2250.0
        },
        {
            "current": 3382.867,
            "min": 1500.0,
            "max": 2250.0
        },
        {
            "current": 3385.712,
            "min": 1500.0,
            "max": 2250.0
        },
        {
            "current": 3392.917,
            "min": 1500.0,
            "max": 2250.0
        },
        {
            "current": 3395.437,
            "min": 1500.0,
            "max": 2250.0
        },
        {
            "current": 2390.521,
            "min": 1500.0,
            "max": 2250.0
        },
        {
            "current": 3223.454,
            "min": 1500.0,
            "max": 2250.0
        },
        {
            "current": 3377.043,
            "min": 1500.0,
            "max": 2250.0
        },
        {
            "current": 3384.597,
            "min": 1500.0,
            "max": 2250.0
        },
        {
            "current": 3387.761,
            "min": 1500.0,
            "max": 2250.0
        },
        {
            "current": 3005.204,
            "min": 1500.0,
            "max": 2250.0
        },
        {
            "current": 3389.281,
            "min": 1500.0,
            "max": 2250.0
        },
        {
            "current": 3013.062,
            "min": 1500.0,
            "max": 2250.0
        },
        {
            "current": 3379.951,
            "min": 1500.0,
            "max": 2250.0
        },
        {
            "current": 3402.395,
            "min": 1500.0,
            "max": 2250.0
        },
        {
            "current": 3376.953,
            "min": 1500.0,
            "max": 2250.0
        },
        {
            "current": 3389.383,
            "min": 1500.0,
            "max": 2250.0
        },
        {
            "current": 3383.317,
            "min": 1500.0,
            "max": 2250.0
        },
        {
            "current": 3386.139,
            "min": 1500.0,
            "max": 2250.0
        },
        {
            "current": 3396.612,
            "min": 1500.0,
            "max": 2250.0
        },
        {
            "current": 3393.268,
            "min": 1500.0,
            "max": 2250.0
        },
        {
            "current": 3387.469,
            "min": 1500.0,
            "max": 2250.0
        },
        {
            "current": 3399.478,
            "min": 1500.0,
            "max": 2250.0
        },
        {
            "current": 3393.963,
            "min": 1500.0,
            "max": 2250.0
        },
        {
            "current": 3383.261,
            "min": 1500.0,
            "max": 2250.0
        },
        {
            "current": 3383.321,
            "min": 1500.0,
            "max": 2250.0
        },
        {
            "current": 3388.673,
            "min": 1500.0,
            "max": 2250.0
        },
        {
            "current": 3388.71,
            "min": 1500.0,
            "max": 2250.0
        },
        {
            "current": 3398.475,
            "min": 1500.0,
            "max": 2250.0
        },
        {
            "current": 3377.946,
            "min": 1500.0,
            "max": 2250.0
        },
        {
            "current": 3390.683,
            "min": 1500.0,
            "max": 2250.0
        },
        {
            "current": 3391.813,
            "min": 1500.0,
            "max": 2250.0
        },
        {
            "current": 3316.582,
            "min": 1500.0,
            "max": 2250.0
        },
        {
            "current": 3278.061,
            "min": 1500.0,
            "max": 2250.0
        },
        {
            "current": 3379.816,
            "min": 1500.0,
            "max": 2250.0
        },
        {
            "current": 2473.514,
            "min": 1500.0,
            "max": 2250.0
        },
        {
            "current": 2477.227,
            "min": 1500.0,
            "max": 2250.0
        },
        {
            "current": 3389.432,
            "min": 1500.0,
            "max": 2250.0
        },
        {
            "current": 3324.924,
            "min": 1500.0,
            "max": 2250.0
        },
        {
            "current": 3373.222,
            "min": 1500.0,
            "max": 2250.0
        },
        {
            "current": 3388.356,
            "min": 1500.0,
            "max": 2250.0
        },
        {
            "current": 2731.757,
            "min": 1500.0,
            "max": 2250.0
        },
        {
            "current": 3390.14,
            "min": 1500.0,
            "max": 2250.0
        },
        {
            "current": 3390.523,
            "min": 1500.0,
            "max": 2250.0
        },
        {
            "current": 2470.868,
            "min": 1500.0,
            "max": 2250.0
        },
        {
            "current": 2480.211,
            "min": 1500.0,
            "max": 2250.0
        },
        {
            "current": 2464.751,
            "min": 1500.0,
            "max": 2250.0
        },
        {
            "current": 3387.714,
            "min": 1500.0,
            "max": 2250.0
        },
        {
            "current": 1736.27,
            "min": 1500.0,
            "max": 2250.0
        },
        {
            "current": 1746.731,
            "min": 1500.0,
            "max": 2250.0
        },
        {
            "current": 3278.685,
            "min": 1500.0,
            "max": 2250.0
        },
        {
            "current": 2924.88,
            "min": 1500.0,
            "max": 2250.0
        },
        {
            "current": 3183.834,
            "min": 1500.0,
            "max": 2250.0
        },
        {
            "current": 1748.467,
            "min": 1500.0,
            "max": 2250.0
        },
        {
            "current": 3297.084,
            "min": 1500.0,
            "max": 2250.0
        },
        {
            "current": 1746.096,
            "min": 1500.0,
            "max": 2250.0
        },
        {
            "current": 3392.232,
            "min": 1500.0,
            "max": 2250.0
        },
        {
            "current": 2408.503,
            "min": 1500.0,
            "max": 2250.0
        },
        {
            "current": 3281.719,
            "min": 1500.0,
            "max": 2250.0
        },
        {
            "current": 3373.216,
            "min": 1500.0,
            "max": 2250.0
        },
        {
            "current": 3077.878,
            "min": 1500.0,
            "max": 2250.0
        },
        {
            "current": 1694.832,
            "min": 1500.0,
            "max": 2250.0
        },
        {
            "current": 3093.378,
            "min": 1500.0,
            "max": 2250.0
        },
        {
            "current": 1700.004,
            "min": 1500.0,
            "max": 2250.0
        }
    ],
    "disk": {
        "/": {
            "total": 1757.8287315368652,
            "used": 422.26829528808594
        }
    },
    "memory": {
        "total": 1007.6966590881348
    }
}
