{
    "os": "Linux-5.4.0-80-generic-x86_64-with-glibc2.31",
    "python": "3.10.14",
    "heartbeatAt": "2024-05-20T11:13:55.213029",
    "startedAt": "2024-05-20T11:13:54.358666",
    "docker": null,
    "cuda": null,
    "args": [
        "--activation=tanh",
        "--alpha=0.0001",
        "--batch_size=32",
        "--beta1=0.99",
        "--epochs=10",
        "--hidden_sizes=128",
        "--learning_rate=1e-05",
        "--loss=cross_entropy",
        "--num_layers=5",
        "--optimizer=nadam",
        "--weight_init=he"
    ],
    "state": "running",
    "program": "/nlsasfs/home/ai4bharat/praveens/srija/assignment_1/train.py",
    "codePathLocal": "train.py",
    "codePath": "train.py",
    "host": "scn28-mn",
    "username": "praveens",
    "executable": "/nlsasfs/home/ai4bharat/praveens/miniconda3/envs/dl_as/bin/python",
    "cpu_count": 128,
    "cpu_count_logical": 256,
    "cpu_freq": {
        "current": 3198.8419140624974,
        "min": 1500.0,
        "max": 2250.0
    },
    "cpu_freq_per_core": [
        {
            "current": 3311.49,
            "min": 1500.0,
            "max": 2250.0
        },
        {
            "current": 3310.905,
            "min": 1500.0,
            "max": 2250.0
        },
        {
            "current": 3311.401,
            "min": 1500.0,
            "max": 2250.0
        },
        {
            "current": 3311.2,
            "min": 1500.0,
            "max": 2250.0
        },
        {
            "current": 3322.997,
            "min": 1500.0,
            "max": 2250.0
        },
        {
            "current": 3322.86,
            "min": 1500.0,
            "max": 2250.0
        },
        {
            "current": 3322.905,
            "min": 1500.0,
            "max": 2250.0
        },
        {
            "current": 3322.761,
            "min": 1500.0,
            "max": 2250.0
        },
        {
            "current": 3373.662,
            "min": 1500.0,
            "max": 2250.0
        },
        {
            "current": 2245.757,
            "min": 1500.0,
            "max": 2250.0
        },
        {
            "current": 2252.772,
            "min": 1500.0,
            "max": 2250.0
        },
        {
            "current": 2279.025,
            "min": 1500.0,
            "max": 2250.0
        },
        {
            "current": 3049.759,
            "min": 1500.0,
            "max": 2250.0
        },
        {
            "current": 3369.316,
            "min": 1500.0,
            "max": 2250.0
        },
        {
            "current": 3376.364,
            "min": 1500.0,
            "max": 2250.0
        },
        {
            "current": 3376.687,
            "min": 1500.0,
            "max": 2250.0
        },
        {
            "current": 3346.828,
            "min": 1500.0,
            "max": 2250.0
        },
        {
            "current": 3346.698,
            "min": 1500.0,
            "max": 2250.0
        },
        {
            "current": 3346.672,
            "min": 1500.0,
            "max": 2250.0
        },
        {
            "current": 3346.782,
            "min": 1500.0,
            "max": 2250.0
        },
        {
            "current": 3329.349,
            "min": 1500.0,
            "max": 2250.0
        },
        {
            "current": 3330.023,
            "min": 1500.0,
            "max": 2250.0
        },
        {
            "current": 3329.887,
            "min": 1500.0,
            "max": 2250.0
        },
        {
            "current": 3330.012,
            "min": 1500.0,
            "max": 2250.0
        },
        {
            "current": 2392.466,
            "min": 1500.0,
            "max": 2250.0
        },
        {
            "current": 2269.755,
            "min": 1500.0,
            "max": 2250.0
        },
        {
            "current": 2288.635,
            "min": 1500.0,
            "max": 2250.0
        },
        {
            "current": 2272.952,
            "min": 1500.0,
            "max": 2250.0
        },
        {
            "current": 3289.426,
            "min": 1500.0,
            "max": 2250.0
        },
        {
            "current": 3371.449,
            "min": 1500.0,
            "max": 2250.0
        },
        {
            "current": 2258.435,
            "min": 1500.0,
            "max": 2250.0
        },
        {
            "current": 2237.304,
            "min": 1500.0,
            "max": 2250.0
        },
        {
            "current": 3389.128,
            "min": 1500.0,
            "max": 2250.0
        },
        {
            "current": 3387.268,
            "min": 1500.0,
            "max": 2250.0
        },
        {
            "current": 3371.6,
            "min": 1500.0,
            "max": 2250.0
        },
        {
            "current": 3295.078,
            "min": 1500.0,
            "max": 2250.0
        },
        {
            "current": 3389.101,
            "min": 1500.0,
            "max": 2250.0
        },
        {
            "current": 3392.048,
            "min": 1500.0,
            "max": 2250.0
        },
        {
            "current": 3364.897,
            "min": 1500.0,
            "max": 2250.0
        },
        {
            "current": 3379.868,
            "min": 1500.0,
            "max": 2250.0
        },
        {
            "current": 3370.168,
            "min": 1500.0,
            "max": 2250.0
        },
        {
            "current": 3373.489,
            "min": 1500.0,
            "max": 2250.0
        },
        {
            "current": 3362.084,
            "min": 1500.0,
            "max": 2250.0
        },
        {
            "current": 3218.192,
            "min": 1500.0,
            "max": 2250.0
        },
        {
            "current": 3369.505,
            "min": 1500.0,
            "max": 2250.0
        },
        {
            "current": 2536.296,
            "min": 1500.0,
            "max": 2250.0
        },
        {
            "current": 3386.171,
            "min": 1500.0,
            "max": 2250.0
        },
        {
            "current": 3369.118,
            "min": 1500.0,
            "max": 2250.0
        },
        {
            "current": 3373.67,
            "min": 1500.0,
            "max": 2250.0
        },
        {
            "current": 3368.068,
            "min": 1500.0,
            "max": 2250.0
        },
        {
            "current": 3369.155,
            "min": 1500.0,
            "max": 2250.0
        },
        {
            "current": 3389.245,
            "min": 1500.0,
            "max": 2250.0
        },
        {
            "current": 3370.662,
            "min": 1500.0,
            "max": 2250.0
        },
        {
            "current": 3377.638,
            "min": 1500.0,
            "max": 2250.0
        },
        {
            "current": 1758.778,
            "min": 1500.0,
            "max": 2250.0
        },
        {
            "current": 3383.999,
            "min": 1500.0,
            "max": 2250.0
        },
        {
            "current": 3377.992,
            "min": 1500.0,
            "max": 2250.0
        },
        {
            "current": 2191.597,
            "min": 1500.0,
            "max": 2250.0
        },
        {
            "current": 2225.731,
            "min": 1500.0,
            "max": 2250.0
        },
        {
            "current": 2220.475,
            "min": 1500.0,
            "max": 2250.0
        },
        {
            "current": 3381.287,
            "min": 1500.0,
            "max": 2250.0
        },
        {
            "current": 2193.841,
            "min": 1500.0,
            "max": 2250.0
        },
        {
            "current": 3314.324,
            "min": 1500.0,
            "max": 2250.0
        },
        {
            "current": 2217.053,
            "min": 1500.0,
            "max": 2250.0
        },
        {
            "current": 2487.062,
            "min": 1500.0,
            "max": 2250.0
        },
        {
            "current": 2508.299,
            "min": 1500.0,
            "max": 2250.0
        },
        {
            "current": 3403.035,
            "min": 1500.0,
            "max": 2250.0
        },
        {
            "current": 2502.571,
            "min": 1500.0,
            "max": 2250.0
        },
        {
            "current": 3384.213,
            "min": 1500.0,
            "max": 2250.0
        },
        {
            "current": 3315.651,
            "min": 1500.0,
            "max": 2250.0
        },
        {
            "current": 2406.236,
            "min": 1500.0,
            "max": 2250.0
        },
        {
            "current": 2381.977,
            "min": 1500.0,
            "max": 2250.0
        },
        {
            "current": 2575.373,
            "min": 1500.0,
            "max": 2250.0
        },
        {
            "current": 2586.719,
            "min": 1500.0,
            "max": 2250.0
        },
        {
            "current": 2565.965,
            "min": 1500.0,
            "max": 2250.0
        },
        {
            "current": 2538.515,
            "min": 1500.0,
            "max": 2250.0
        },
        {
            "current": 3397.678,
            "min": 1500.0,
            "max": 2250.0
        },
        {
            "current": 3399.651,
            "min": 1500.0,
            "max": 2250.0
        },
        {
            "current": 3396.707,
            "min": 1500.0,
            "max": 2250.0
        },
        {
            "current": 3395.471,
            "min": 1500.0,
            "max": 2250.0
        },
        {
            "current": 3387.417,
            "min": 1500.0,
            "max": 2250.0
        },
        {
            "current": 3397.931,
            "min": 1500.0,
            "max": 2250.0
        },
        {
            "current": 3254.27,
            "min": 1500.0,
            "max": 2250.0
        },
        {
            "current": 2042.621,
            "min": 1500.0,
            "max": 2250.0
        },
        {
            "current": 3384.277,
            "min": 1500.0,
            "max": 2250.0
        },
        {
            "current": 3393.221,
            "min": 1500.0,
            "max": 2250.0
        },
        {
            "current": 3396.255,
            "min": 1500.0,
            "max": 2250.0
        },
        {
            "current": 3394.768,
            "min": 1500.0,
            "max": 2250.0
        },
        {
            "current": 2456.077,
            "min": 1500.0,
            "max": 2250.0
        },
        {
            "current": 3387.268,
            "min": 1500.0,
            "max": 2250.0
        },
        {
            "current": 2492.111,
            "min": 1500.0,
            "max": 2250.0
        },
        {
            "current": 3397.153,
            "min": 1500.0,
            "max": 2250.0
        },
        {
            "current": 2522.832,
            "min": 1500.0,
            "max": 2250.0
        },
        {
            "current": 2462.412,
            "min": 1500.0,
            "max": 2250.0
        },
        {
            "current": 3391.83,
            "min": 1500.0,
            "max": 2250.0
        },
        {
            "current": 2461.267,
            "min": 1500.0,
            "max": 2250.0
        },
        {
            "current": 3391.708,
            "min": 1500.0,
            "max": 2250.0
        },
        {
            "current": 3392.135,
            "min": 1500.0,
            "max": 2250.0
        },
        {
            "current": 3390.465,
            "min": 1500.0,
            "max": 2250.0
        },
        {
            "current": 3393.428,
            "min": 1500.0,
            "max": 2250.0
        },
        {
            "current": 3389.689,
            "min": 1500.0,
            "max": 2250.0
        },
        {
            "current": 3389.176,
            "min": 1500.0,
            "max": 2250.0
        },
        {
            "current": 3393.12,
            "min": 1500.0,
            "max": 2250.0
        },
        {
            "current": 3391.566,
            "min": 1500.0,
            "max": 2250.0
        },
        {
            "current": 2906.031,
            "min": 1500.0,
            "max": 2250.0
        },
        {
            "current": 3385.823,
            "min": 1500.0,
            "max": 2250.0
        },
        {
            "current": 3353.319,
            "min": 1500.0,
            "max": 2250.0
        },
        {
            "current": 3392.614,
            "min": 1500.0,
            "max": 2250.0
        },
        {
            "current": 3373.995,
            "min": 1500.0,
            "max": 2250.0
        },
        {
            "current": 3352.61,
            "min": 1500.0,
            "max": 2250.0
        },
        {
            "current": 3340.176,
            "min": 1500.0,
            "max": 2250.0
        },
        {
            "current": 3390.94,
            "min": 1500.0,
            "max": 2250.0
        },
        {
            "current": 2696.185,
            "min": 1500.0,
            "max": 2250.0
        },
        {
            "current": 2709.047,
            "min": 1500.0,
            "max": 2250.0
        },
        {
            "current": 2583.508,
            "min": 1500.0,
            "max": 2250.0
        },
        {
            "current": 2493.69,
            "min": 1500.0,
            "max": 2250.0
        },
        {
            "current": 3392.881,
            "min": 1500.0,
            "max": 2250.0
        },
        {
            "current": 3391.224,
            "min": 1500.0,
            "max": 2250.0
        },
        {
            "current": 3381.501,
            "min": 1500.0,
            "max": 2250.0
        },
        {
            "current": 3393.577,
            "min": 1500.0,
            "max": 2250.0
        },
        {
            "current": 3056.03,
            "min": 1500.0,
            "max": 2250.0
        },
        {
            "current": 2969.521,
            "min": 1500.0,
            "max": 2250.0
        },
        {
            "current": 3392.558,
            "min": 1500.0,
            "max": 2250.0
        },
        {
            "current": 2884.476,
            "min": 1500.0,
            "max": 2250.0
        },
        {
            "current": 3251.077,
            "min": 1500.0,
            "max": 2250.0
        },
        {
            "current": 3393.558,
            "min": 1500.0,
            "max": 2250.0
        },
        {
            "current": 3372.541,
            "min": 1500.0,
            "max": 2250.0
        },
        {
            "current": 3382.089,
            "min": 1500.0,
            "max": 2250.0
        },
        {
            "current": 3308.429,
            "min": 1500.0,
            "max": 2250.0
        },
        {
            "current": 3307.843,
            "min": 1500.0,
            "max": 2250.0
        },
        {
            "current": 3308.357,
            "min": 1500.0,
            "max": 2250.0
        },
        {
            "current": 3308.216,
            "min": 1500.0,
            "max": 2250.0
        },
        {
            "current": 3319.858,
            "min": 1500.0,
            "max": 2250.0
        },
        {
            "current": 3319.801,
            "min": 1500.0,
            "max": 2250.0
        },
        {
            "current": 3319.795,
            "min": 1500.0,
            "max": 2250.0
        },
        {
            "current": 3319.833,
            "min": 1500.0,
            "max": 2250.0
        },
        {
            "current": 3363.812,
            "min": 1500.0,
            "max": 2250.0
        },
        {
            "current": 2528.723,
            "min": 1500.0,
            "max": 2250.0
        },
        {
            "current": 3291.218,
            "min": 1500.0,
            "max": 2250.0
        },
        {
            "current": 2486.106,
            "min": 1500.0,
            "max": 2250.0
        },
        {
            "current": 3345.93,
            "min": 1500.0,
            "max": 2250.0
        },
        {
            "current": 3367.308,
            "min": 1500.0,
            "max": 2250.0
        },
        {
            "current": 3375.764,
            "min": 1500.0,
            "max": 2250.0
        },
        {
            "current": 3368.316,
            "min": 1500.0,
            "max": 2250.0
        },
        {
            "current": 3345.77,
            "min": 1500.0,
            "max": 2250.0
        },
        {
            "current": 3345.635,
            "min": 1500.0,
            "max": 2250.0
        },
        {
            "current": 3345.636,
            "min": 1500.0,
            "max": 2250.0
        },
        {
            "current": 3345.752,
            "min": 1500.0,
            "max": 2250.0
        },
        {
            "current": 3327.762,
            "min": 1500.0,
            "max": 2250.0
        },
        {
            "current": 3328.439,
            "min": 1500.0,
            "max": 2250.0
        },
        {
            "current": 3328.41,
            "min": 1500.0,
            "max": 2250.0
        },
        {
            "current": 3328.599,
            "min": 1500.0,
            "max": 2250.0
        },
        {
            "current": 2326.214,
            "min": 1500.0,
            "max": 2250.0
        },
        {
            "current": 2273.425,
            "min": 1500.0,
            "max": 2250.0
        },
        {
            "current": 2308.433,
            "min": 1500.0,
            "max": 2250.0
        },
        {
            "current": 2271.129,
            "min": 1500.0,
            "max": 2250.0
        },
        {
            "current": 2666.158,
            "min": 1500.0,
            "max": 2250.0
        },
        {
            "current": 3374.55,
            "min": 1500.0,
            "max": 2250.0
        },
        {
            "current": 2216.657,
            "min": 1500.0,
            "max": 2250.0
        },
        {
            "current": 2195.511,
            "min": 1500.0,
            "max": 2250.0
        },
        {
            "current": 3370.073,
            "min": 1500.0,
            "max": 2250.0
        },
        {
            "current": 3392.14,
            "min": 1500.0,
            "max": 2250.0
        },
        {
            "current": 3364.427,
            "min": 1500.0,
            "max": 2250.0
        },
        {
            "current": 3321.16,
            "min": 1500.0,
            "max": 2250.0
        },
        {
            "current": 3368.38,
            "min": 1500.0,
            "max": 2250.0
        },
        {
            "current": 3373.997,
            "min": 1500.0,
            "max": 2250.0
        },
        {
            "current": 3372.491,
            "min": 1500.0,
            "max": 2250.0
        },
        {
            "current": 3367.756,
            "min": 1500.0,
            "max": 2250.0
        },
        {
            "current": 3370.67,
            "min": 1500.0,
            "max": 2250.0
        },
        {
            "current": 3391.5,
            "min": 1500.0,
            "max": 2250.0
        },
        {
            "current": 3388.16,
            "min": 1500.0,
            "max": 2250.0
        },
        {
            "current": 3371.2,
            "min": 1500.0,
            "max": 2250.0
        },
        {
            "current": 2574.916,
            "min": 1500.0,
            "max": 2250.0
        },
        {
            "current": 2343.53,
            "min": 1500.0,
            "max": 2250.0
        },
        {
            "current": 1751.747,
            "min": 1500.0,
            "max": 2250.0
        },
        {
            "current": 3369.823,
            "min": 1500.0,
            "max": 2250.0
        },
        {
            "current": 3384.387,
            "min": 1500.0,
            "max": 2250.0
        },
        {
            "current": 3385.909,
            "min": 1500.0,
            "max": 2250.0
        },
        {
            "current": 3366.736,
            "min": 1500.0,
            "max": 2250.0
        },
        {
            "current": 3375.683,
            "min": 1500.0,
            "max": 2250.0
        },
        {
            "current": 3377.605,
            "min": 1500.0,
            "max": 2250.0
        },
        {
            "current": 3369.613,
            "min": 1500.0,
            "max": 2250.0
        },
        {
            "current": 3368.86,
            "min": 1500.0,
            "max": 2250.0
        },
        {
            "current": 3368.808,
            "min": 1500.0,
            "max": 2250.0
        },
        {
            "current": 3360.989,
            "min": 1500.0,
            "max": 2250.0
        },
        {
            "current": 3366.902,
            "min": 1500.0,
            "max": 2250.0
        },
        {
            "current": 3361.901,
            "min": 1500.0,
            "max": 2250.0
        },
        {
            "current": 3378.059,
            "min": 1500.0,
            "max": 2250.0
        },
        {
            "current": 3376.088,
            "min": 1500.0,
            "max": 2250.0
        },
        {
            "current": 3368.461,
            "min": 1500.0,
            "max": 2250.0
        },
        {
            "current": 3360.882,
            "min": 1500.0,
            "max": 2250.0
        },
        {
            "current": 3368.809,
            "min": 1500.0,
            "max": 2250.0
        },
        {
            "current": 2589.018,
            "min": 1500.0,
            "max": 2250.0
        },
        {
            "current": 3392.095,
            "min": 1500.0,
            "max": 2250.0
        },
        {
            "current": 3381.711,
            "min": 1500.0,
            "max": 2250.0
        },
        {
            "current": 3392.366,
            "min": 1500.0,
            "max": 2250.0
        },
        {
            "current": 3385.92,
            "min": 1500.0,
            "max": 2250.0
        },
        {
            "current": 3388.58,
            "min": 1500.0,
            "max": 2250.0
        },
        {
            "current": 3391.766,
            "min": 1500.0,
            "max": 2250.0
        },
        {
            "current": 3387.595,
            "min": 1500.0,
            "max": 2250.0
        },
        {
            "current": 3389.692,
            "min": 1500.0,
            "max": 2250.0
        },
        {
            "current": 3393.303,
            "min": 1500.0,
            "max": 2250.0
        },
        {
            "current": 2387.527,
            "min": 1500.0,
            "max": 2250.0
        },
        {
            "current": 3402.583,
            "min": 1500.0,
            "max": 2250.0
        },
        {
            "current": 3122.531,
            "min": 1500.0,
            "max": 2250.0
        },
        {
            "current": 3390.111,
            "min": 1500.0,
            "max": 2250.0
        },
        {
            "current": 3388.873,
            "min": 1500.0,
            "max": 2250.0
        },
        {
            "current": 3392.12,
            "min": 1500.0,
            "max": 2250.0
        },
        {
            "current": 3392.249,
            "min": 1500.0,
            "max": 2250.0
        },
        {
            "current": 3391.164,
            "min": 1500.0,
            "max": 2250.0
        },
        {
            "current": 3392.94,
            "min": 1500.0,
            "max": 2250.0
        },
        {
            "current": 3385.89,
            "min": 1500.0,
            "max": 2250.0
        },
        {
            "current": 3385.686,
            "min": 1500.0,
            "max": 2250.0
        },
        {
            "current": 3410.331,
            "min": 1500.0,
            "max": 2250.0
        },
        {
            "current": 3392.462,
            "min": 1500.0,
            "max": 2250.0
        },
        {
            "current": 2596.359,
            "min": 1500.0,
            "max": 2250.0
        },
        {
            "current": 3388.502,
            "min": 1500.0,
            "max": 2250.0
        },
        {
            "current": 3384.155,
            "min": 1500.0,
            "max": 2250.0
        },
        {
            "current": 3394.72,
            "min": 1500.0,
            "max": 2250.0
        },
        {
            "current": 3375.342,
            "min": 1500.0,
            "max": 2250.0
        },
        {
            "current": 3392.908,
            "min": 1500.0,
            "max": 2250.0
        },
        {
            "current": 3399.053,
            "min": 1500.0,
            "max": 2250.0
        },
        {
            "current": 3387.244,
            "min": 1500.0,
            "max": 2250.0
        },
        {
            "current": 2389.859,
            "min": 1500.0,
            "max": 2250.0
        },
        {
            "current": 3378.961,
            "min": 1500.0,
            "max": 2250.0
        },
        {
            "current": 3389.923,
            "min": 1500.0,
            "max": 2250.0
        },
        {
            "current": 3388.441,
            "min": 1500.0,
            "max": 2250.0
        },
        {
            "current": 3275.471,
            "min": 1500.0,
            "max": 2250.0
        },
        {
            "current": 3392.199,
            "min": 1500.0,
            "max": 2250.0
        },
        {
            "current": 3352.183,
            "min": 1500.0,
            "max": 2250.0
        },
        {
            "current": 3390.476,
            "min": 1500.0,
            "max": 2250.0
        },
        {
            "current": 3393.12,
            "min": 1500.0,
            "max": 2250.0
        },
        {
            "current": 1958.445,
            "min": 1500.0,
            "max": 2250.0
        },
        {
            "current": 3397.661,
            "min": 1500.0,
            "max": 2250.0
        },
        {
            "current": 3391.465,
            "min": 1500.0,
            "max": 2250.0
        },
        {
            "current": 3392.081,
            "min": 1500.0,
            "max": 2250.0
        },
        {
            "current": 3393.077,
            "min": 1500.0,
            "max": 2250.0
        },
        {
            "current": 3392.506,
            "min": 1500.0,
            "max": 2250.0
        },
        {
            "current": 3391.128,
            "min": 1500.0,
            "max": 2250.0
        },
        {
            "current": 3387.583,
            "min": 1500.0,
            "max": 2250.0
        },
        {
            "current": 3025.338,
            "min": 1500.0,
            "max": 2250.0
        },
        {
            "current": 2374.881,
            "min": 1500.0,
            "max": 2250.0
        },
        {
            "current": 2693.376,
            "min": 1500.0,
            "max": 2250.0
        },
        {
            "current": 2732.421,
            "min": 1500.0,
            "max": 2250.0
        },
        {
            "current": 2886.01,
            "min": 1500.0,
            "max": 2250.0
        },
        {
            "current": 3404.415,
            "min": 1500.0,
            "max": 2250.0
        },
        {
            "current": 2974.33,
            "min": 1500.0,
            "max": 2250.0
        },
        {
            "current": 3390.6,
            "min": 1500.0,
            "max": 2250.0
        },
        {
            "current": 2094.199,
            "min": 1500.0,
            "max": 2250.0
        },
        {
            "current": 3395.822,
            "min": 1500.0,
            "max": 2250.0
        },
        {
            "current": 3375.657,
            "min": 1500.0,
            "max": 2250.0
        },
        {
            "current": 2374.318,
            "min": 1500.0,
            "max": 2250.0
        },
        {
            "current": 3393.191,
            "min": 1500.0,
            "max": 2250.0
        },
        {
            "current": 3393.299,
            "min": 1500.0,
            "max": 2250.0
        },
        {
            "current": 3392.675,
            "min": 1500.0,
            "max": 2250.0
        },
        {
            "current": 3387.325,
            "min": 1500.0,
            "max": 2250.0
        }
    ],
    "disk": {
        "/": {
            "total": 1757.8287315368652,
            "used": 422.2677536010742
        }
    },
    "memory": {
        "total": 1007.6966590881348
    }
}
